sqlite_explain/__init__.py
sqlite_explain-0.1a0.dist-info/LICENSE
sqlite_explain-0.1a0.dist-info/METADATA
sqlite_explain-0.1a0.dist-info/WHEEL
sqlite_explain-0.1a0.dist-info/top_level.txt
sqlite_explain-0.1a0.dist-info/RECORD
