Metadata-Version: 2.1
Name: sqlite-explain
Version: 0.1a0
Summary: Derive information about a SQLite query using EXPLAIN
Home-page: https://github.com/simonw/sqlite-explain
Author: Simon Willison
License: Apache License, Version 2.0
Project-URL: Issues, https://github.com/simonw/sqlite-explain/issues
Project-URL: CI, https://github.com/simonw/sqlite-explain/actions
Project-URL: Changelog, https://github.com/simonw/sqlite-explain/releases
Platform: UNKNOWN
Requires-Python: >=3.6
Provides-Extra: test
Requires-Dist: pytest ; extra == 'test'
